cognito-authentication-streamlit-test/__init__.py
cognito-authentication-streamlit-test/authentication.py
cognito-authentication-streamlit-test/decode_verify_jwt.py
cognito_authentication_streamlit/__init__.py
cognito_authentication_streamlit/authentication.py
cognito_authentication_streamlit/decode_verify_jwt.py
streamlit_cognito_token_access_authentication/__init__.py
streamlit_cognito_token_access_authentication/authentication.py
streamlit_cognito_token_access_authentication/decode_verify_jwt.py
streamlit_cognito_token_access_authentication-1.1.17.dist-info/METADATA
streamlit_cognito_token_access_authentication-1.1.17.dist-info/WHEEL
streamlit_cognito_token_access_authentication-1.1.17.dist-info/top_level.txt
streamlit_cognito_token_access_authentication-1.1.17.dist-info/RECORD
